chgksuite_tk/__main__.py
chgksuite_tk/gui.py
chgksuite_tk/version.py
chgksuite_tk-0.0.1.dist-info/LICENSE
chgksuite_tk-0.0.1.dist-info/METADATA
chgksuite_tk-0.0.1.dist-info/WHEEL
chgksuite_tk-0.0.1.dist-info/entry_points.txt
chgksuite_tk-0.0.1.dist-info/top_level.txt
chgksuite_tk-0.0.1.dist-info/RECORD
