Metadata-Version: 2.1
Name: chgksuite_tk
Version: 0.0.1
Summary: A GUI wrapper for chgksuite using tkinter
Home-page: https://gitlab.com/peczony/chgksuite_tk
Author: Alexander Pecheny
Author-email: ap@pecheny.me
Classifier: Programming Language :: Python :: 3
Classifier: License :: OSI Approved :: MIT License
Classifier: Operating System :: OS Independent
License-File: LICENSE
Requires-Dist: chgksuite
